{
    "type": "User Profile",
    "name": "Alcrano",
    "config": "{\"signature\":{\"message\":\"Alcrano\",\"messageHash\":\"0x44b8e61bab2d30dcb8de21fc17ab114a783a0abf8ac33a9ed35b82f3937658ae\",\"v\":\"0x1b\",\"r\":\"0x0a532ad117c72ddb905151e61ff999267180b985fb3037eaca47814f6c2c0475\",\"s\":\"0x1232bc97b096642cc497bd0577bc475a363590c97b6ef30ad04db57d36b55626\",\"signature\":\"0x0a532ad117c72ddb905151e61ff999267180b985fb3037eaca47814f6c2c04751232bc97b096642cc497bd0577bc475a363590c97b6ef30ad04db57d36b556261b\"},\"codeName\":\"Alcrano\"}",
    "project": "Governance",
    "tokenPowerSwitch": {
        "type": "Token Power Switch",
        "name": "New Token Power Switch",
        "config": "{}",
        "project": "Governance",
        "tokenPowerSwitch": [],
        "financialPrograms": {
            "type": "Financial Programs",
            "name": "New Financial Programs",
            "config": "{}",
            "project": "Governance",
            "stakingProgram": {
                "type": "Staking Program",
                "name": "New Staking Program",
                "config": "{}",
                "project": "Governance",
                "tokensAwarded": {
                    "type": "Tokens Awarded",
                    "name": "New Tokens Awarded",
                    "project": "Governance",
                    "id": "aa1436a4-14f0-419e-b06c-d814dcb2bdf7",
                    "savedPayload": {
                        "position": {
                            "x": 34412.756196739334,
                            "y": 18350
                        },
                        "targetPosition": {
                            "x": 34152.948575604,
                            "y": 18500
                        },
                        "floatingObject": {
                            "isPinned": false,
                            "isFrozen": false,
                            "isCollapsed": false,
                            "angleToParent": 2,
                            "distanceToParent": 3,
                            "arrangementStyle": 0
                        },
                        "uiObject": {
                            "isRunning": false
                        }
                    }
                },
                "id": "097fcc82-4d53-4153-af82-723f377a4a9c",
                "savedPayload": {
                    "position": {
                        "x": 34152.948575604,
                        "y": 18500
                    },
                    "targetPosition": {
                        "x": 33893.14095446867,
                        "y": 18650
                    },
                    "floatingObject": {
                        "isPinned": false,
                        "isFrozen": false,
                        "isCollapsed": false,
                        "angleToParent": 2,
                        "distanceToParent": 3,
                        "arrangementStyle": 0
                    },
                    "uiObject": {
                        "isRunning": false
                    }
                }
            },
            "id": "9360b6b5-ca67-4059-8c84-cee883942b6a",
            "savedPayload": {
                "position": {
                    "x": 33893.14095446867,
                    "y": 18650
                },
                "targetPosition": {
                    "x": 33633.333333333336,
                    "y": 18800
                },
                "floatingObject": {
                    "isPinned": false,
                    "isFrozen": false,
                    "isCollapsed": false,
                    "angleToParent": 2,
                    "distanceToParent": 3,
                    "arrangementStyle": 0
                },
                "uiObject": {
                    "isRunning": false
                }
            }
        },
        "liquidityPrograms": {
            "type": "Liquidity Programs",
            "name": "New Liquidity Programs",
            "config": "{}",
            "project": "Governance",
            "liquidityProgram": [
                {
                    "type": "Liquidity Program",
                    "name": "New Liquidity Program",
                    "config": "{\n\"asset\": \"BTCB\"\n}",
                    "project": "Governance",
                    "tokensAwarded": {
                        "type": "Tokens Awarded",
                        "name": "New Tokens Awarded",
                        "project": "Governance",
                        "id": "236f2fe8-6af3-47a8-9800-dff4b056843e",
                        "savedPayload": {
                            "position": {
                                "x": 34412.756196739334,
                                "y": 19250
                            },
                            "targetPosition": {
                                "x": 34152.948575604,
                                "y": 19100
                            },
                            "floatingObject": {
                                "isPinned": false,
                                "isFrozen": false,
                                "isCollapsed": false,
                                "angleToParent": 2,
                                "distanceToParent": 3,
                                "arrangementStyle": 0
                            },
                            "uiObject": {
                                "isRunning": false
                            }
                        }
                    },
                    "id": "629521fb-ee16-4318-8bb5-78adb8d80a9e",
                    "savedPayload": {
                        "position": {
                            "x": 34152.948575604,
                            "y": 19100
                        },
                        "targetPosition": {
                            "x": 33893.14095446867,
                            "y": 18950
                        },
                        "floatingObject": {
                            "isPinned": false,
                            "isFrozen": false,
                            "isCollapsed": false,
                            "angleToParent": 2,
                            "distanceToParent": 3,
                            "arrangementStyle": 0
                        },
                        "uiObject": {
                            "isRunning": false
                        }
                    }
                }
            ],
            "id": "ac899fa6-d86b-4ffa-8f6b-2154362f2e52",
            "savedPayload": {
                "position": {
                    "x": 33893.14095446867,
                    "y": 18950
                },
                "targetPosition": {
                    "x": 33633.333333333336,
                    "y": 18800
                },
                "floatingObject": {
                    "isPinned": false,
                    "isFrozen": false,
                    "isCollapsed": false,
                    "angleToParent": 2,
                    "distanceToParent": 3,
                    "arrangementStyle": 0
                },
                "uiObject": {
                    "isRunning": false
                }
            }
        },
        "id": "3955f48f-c72f-4fc7-8543-eb92590978d9",
        "savedPayload": {
            "position": {
                "x": 30300,
                "y": 28400
            },
            "targetPosition": {
                "x": 30000,
                "y": 28400
            },
            "floatingObject": {
                "isPinned": false,
                "isFrozen": false,
                "isCollapsed": true,
                "angleToParent": 1,
                "distanceToParent": 3,
                "arrangementStyle": 0
            },
            "uiObject": {
                "isRunning": false
            }
        }
    },
    "tokensMined": {
        "type": "Tokens Mined",
        "name": "New Tokens Mined",
        "project": "Governance",
        "id": "e08e1f3b-0a4c-4e82-a92d-fcf16f8ca63a",
        "savedPayload": {
            "position": {
                "x": 30150,
                "y": 28659.807621135333
            },
            "targetPosition": {
                "x": 30000,
                "y": 28400
            },
            "floatingObject": {
                "isPinned": false,
                "isFrozen": false,
                "isCollapsed": false,
                "angleToParent": 1,
                "distanceToParent": 3,
                "arrangementStyle": 0
            },
            "uiObject": {
                "isRunning": false
            }
        }
    },
    "userApps": {
        "type": "User Apps",
        "name": "New User Apps",
        "config": "{}",
        "project": "User-Apps",
        "desktopApps": {
            "type": "Desktop Apps",
            "name": "New Desktop Apps",
            "config": "{}",
            "project": "User-Apps",
            "socialTradingDesktopApps": [
                {
                    "type": "Social Trading Desktop App",
                    "name": "Social Trading Desktop App #1",
                    "config": "{\n    \"codeName\": \"Social-Trading-Desktop-App-1\",\n    \"host\": \"localhost\",\n    \"webPort\": \"33248\",\n    \"webSocketsPort\": \"17042\"\n}",
                    "project": "User-Apps",
                    "signingAccount": {
                        "type": "Signing Account",
                        "name": "New Signing Account",
                        "config": "{\n    \"codeName\": \"Social-Trading-Desktop-App-1\",\n    \"signature\": {\n        \"message\": \"Alcrano\",\n        \"messageHash\": \"0x44b8e61bab2d30dcb8de21fc17ab114a783a0abf8ac33a9ed35b82f3937658ae\",\n        \"v\": \"0x1c\",\n        \"r\": \"0x6425da926df01673409f088de0cf8d65e3db4330a205f81d80ff2cd5d66bd473\",\n        \"s\": \"0x62fdc911ced32763640cb36e0510c216f197fbc8f21b5f4906126d08875fe143\",\n        \"signature\": \"0x6425da926df01673409f088de0cf8d65e3db4330a205f81d80ff2cd5d66bd47362fdc911ced32763640cb36e0510c216f197fbc8f21b5f4906126d08875fe1431c\"\n    }\n}",
                        "project": "Governance",
                        "id": "49e9e585-066b-4ade-a94c-a55d715c2fa8",
                        "savedPayload": {
                            "position": {
                                "x": 29400,
                                "y": 29439.23048454133
                            },
                            "targetPosition": {
                                "x": 29550,
                                "y": 29179.422863406
                            },
                            "floatingObject": {
                                "isPinned": false,
                                "isFrozen": false,
                                "isCollapsed": false,
                                "angleToParent": 1,
                                "distanceToParent": 3,
                                "arrangementStyle": 0
                            },
                            "uiObject": {
                                "isRunning": false
                            }
                        }
                    },
                    "id": "9f89caef-c5e9-46d7-b993-5e8cff767f6c",
                    "savedPayload": {
                        "position": {
                            "x": 29550,
                            "y": 29179.422863406
                        },
                        "targetPosition": {
                            "x": 29700,
                            "y": 28919.615242270665
                        },
                        "floatingObject": {
                            "isPinned": false,
                            "isFrozen": false,
                            "isCollapsed": false,
                            "angleToParent": 1,
                            "distanceToParent": 3,
                            "arrangementStyle": 0
                        },
                        "uiObject": {
                            "isRunning": false
                        }
                    }
                }
            ],
            "algoTradesPlatformApp": [],
            "id": "38434943-ef82-47ac-9a32-223ed79bd1a6",
            "savedPayload": {
                "position": {
                    "x": 29700,
                    "y": 28919.615242270665
                },
                "targetPosition": {
                    "x": 29850,
                    "y": 28659.807621135333
                },
                "floatingObject": {
                    "isPinned": false,
                    "isFrozen": false,
                    "isCollapsed": false,
                    "angleToParent": 1,
                    "distanceToParent": 3,
                    "arrangementStyle": 0
                },
                "uiObject": {
                    "isRunning": false
                }
            }
        },
        "id": "d7293328-d28b-430c-b132-7f64726bf951",
        "savedPayload": {
            "position": {
                "x": 29850,
                "y": 28659.807621135333
            },
            "targetPosition": {
                "x": 30000,
                "y": 28400
            },
            "floatingObject": {
                "isPinned": false,
                "isFrozen": false,
                "isCollapsed": false,
                "angleToParent": 1,
                "distanceToParent": 3,
                "arrangementStyle": 0
            },
            "uiObject": {
                "isRunning": false
            }
        }
    },
    "socialPersonas": {
        "type": "Social Personas",
        "name": "New Social Personas",
        "config": "{}",
        "project": "Social-Trading",
        "socialPersonas": [
            {
                "type": "Social Persona",
                "name": "Social Persona #1",
                "config": "{\n    \"codeName\": \"Social-Persona-1\",\n    \"handle\": \"Alcrano-Social-Persona-1\"\n}",
                "project": "Social-Trading",
                "signingAccount": {
                    "type": "Signing Account",
                    "name": "New Signing Account",
                    "config": "{\n    \"codeName\": \"Social-Persona-1\",\n    \"signature\": {\n        \"message\": \"Alcrano\",\n        \"messageHash\": \"0x44b8e61bab2d30dcb8de21fc17ab114a783a0abf8ac33a9ed35b82f3937658ae\",\n        \"v\": \"0x1b\",\n        \"r\": \"0x175c21943b7792f198080a062343a0520ce91052b41ecb19b30512601be514a2\",\n        \"s\": \"0x7896b903efe17d7b6cd29401f6814da19f3d1b5f62240839cf5d15eb9a0e97f6\",\n        \"signature\": \"0x175c21943b7792f198080a062343a0520ce91052b41ecb19b30512601be514a27896b903efe17d7b6cd29401f6814da19f3d1b5f62240839cf5d15eb9a0e97f61b\"\n    }\n}",
                    "project": "Governance",
                    "id": "47cf8b4d-a2ac-4449-8318-ea7ca8f29ae7",
                    "savedPayload": {
                        "position": {
                            "x": 29250,
                            "y": 28659.807621135333
                        },
                        "targetPosition": {
                            "x": 29400,
                            "y": 28400
                        },
                        "floatingObject": {
                            "isPinned": false,
                            "isFrozen": false,
                            "isCollapsed": false,
                            "angleToParent": 1,
                            "distanceToParent": 3,
                            "arrangementStyle": 0
                        },
                        "uiObject": {
                            "isRunning": false
                        }
                    }
                },
                "availableStorage": {
                    "type": "Available Storage",
                    "name": "New Available Storage",
                    "config": "{}",
                    "project": "Open-Storage",
                    "storageContainerReferences": [
                        {
                            "type": "Storage Container Reference",
                            "name": "Social Trading Data",
                            "config": "{}",
                            "project": "Open-Storage",
                            "id": "05d8c344-a884-4f01-9b74-9319a7e647ad",
                            "savedPayload": {
                                "position": {
                                    "x": 29100,
                                    "y": 27880.384757729335
                                },
                                "targetPosition": {
                                    "x": 29250,
                                    "y": 28140.192378864667
                                },
                                "floatingObject": {
                                    "isPinned": false,
                                    "isFrozen": false,
                                    "isCollapsed": false,
                                    "angleToParent": 1,
                                    "distanceToParent": 3,
                                    "arrangementStyle": 0
                                },
                                "uiObject": {
                                    "isRunning": false
                                },
                                "referenceParent": {
                                    "type": "Github Storage Container",
                                    "name": "Social Trading Data",
                                    "id": "c89c79ff-273b-4a4d-b455-55a9ff0145ba"
                                },
                                "referenceParentCombinedNodePath": [
                                    [
                                        "Alcrano",
                                        "User Profile"
                                    ],
                                    [
                                        "New User Storage",
                                        "User Storage"
                                    ],
                                    [
                                        "New Github Storage",
                                        "Github Storage"
                                    ],
                                    [
                                        "Social Trading Data",
                                        "Github Storage Container"
                                    ]
                                ]
                            }
                        }
                    ],
                    "id": "ecdee7ed-8611-4ce2-a03d-b6db95ee99cf",
                    "savedPayload": {
                        "position": {
                            "x": 29250,
                            "y": 28140.192378864667
                        },
                        "targetPosition": {
                            "x": 29400,
                            "y": 28400
                        },
                        "floatingObject": {
                            "isPinned": false,
                            "isFrozen": false,
                            "isCollapsed": false,
                            "angleToParent": 1,
                            "distanceToParent": 3,
                            "arrangementStyle": 0
                        },
                        "uiObject": {
                            "isRunning": false
                        }
                    }
                },
                "id": "24998fa4-9ab5-4eab-9c3f-f6e92ad28209",
                "savedPayload": {
                    "position": {
                        "x": 29400,
                        "y": 28400
                    },
                    "targetPosition": {
                        "x": 29700,
                        "y": 28400
                    },
                    "floatingObject": {
                        "isPinned": false,
                        "isFrozen": false,
                        "isCollapsed": false,
                        "angleToParent": 1,
                        "distanceToParent": 3,
                        "arrangementStyle": 0
                    },
                    "uiObject": {
                        "isRunning": false
                    }
                }
            }
        ],
        "id": "8bb9e2ae-8c4d-46cc-9b94-902d15a34cb8",
        "savedPayload": {
            "position": {
                "x": 29700,
                "y": 28400
            },
            "targetPosition": {
                "x": 30000,
                "y": 28400
            },
            "floatingObject": {
                "isPinned": false,
                "isFrozen": false,
                "isCollapsed": false,
                "angleToParent": 1,
                "distanceToParent": 3,
                "arrangementStyle": 0
            },
            "uiObject": {
                "isRunning": false
            }
        }
    },
    "p2pNetworkNodes": {
        "type": "P2P Network Nodes",
        "name": "New P2P Network Nodes",
        "config": "{}",
        "project": "Network",
        "p2pNetworkNodes": [
            {
                "type": "P2P Network Node",
                "name": "New P2P Network Node",
                "config": "{ \n\"codeName\": \"\", \n\"host\": \"localhost\", \n\"clientMinimunBalance\": 0, \n\"clientMinimunBalance\": 0 \n}",
                "project": "Network",
                "p2pNetworkReference": {
                    "type": "P2P Network Reference",
                    "name": "Testnet",
                    "project": "Network",
                    "id": "69240cc8-8e15-4f2f-bb89-2bb98ac9eb5a",
                    "savedPayload": {
                        "position": {
                            "x": 29410.22225211328,
                            "y": 27802.739044198577
                        },
                        "targetPosition": {
                            "x": 29700,
                            "y": 27880.384757729335
                        },
                        "floatingObject": {
                            "isPinned": false,
                            "isFrozen": false,
                            "isCollapsed": false,
                            "angleToParent": 2,
                            "distanceToParent": 3,
                            "arrangementStyle": 0
                        },
                        "uiObject": {
                            "isRunning": false
                        },
                        "referenceParent": {
                            "type": "P2P Network",
                            "name": "Testnet",
                            "id": "8cf3c984-f2ce-4ed5-9bfe-49255ed8a9e3"
                        },
                        "referenceParentCombinedNodePath": [
                            [
                                "Testnet",
                                "P2P Network"
                            ]
                        ]
                    }
                },
                "networkServices": {
                    "type": "Network Services",
                    "name": "New Network Services",
                    "config": "{}",
                    "project": "Network",
                    "socialGraph": {
                        "type": "Social Graph",
                        "name": "New Social Graph",
                        "config": "{}",
                        "project": "Network",
                        "id": "7a1d26e4-24d4-4d2b-9597-0e70663a9aad",
                        "savedPayload": {
                            "position": {
                                "x": 29290.192378864667,
                                "y": 27470.577136594
                            },
                            "targetPosition": {
                                "x": 29550,
                                "y": 27620.577136594
                            },
                            "floatingObject": {
                                "isPinned": false,
                                "isFrozen": false,
                                "isCollapsed": false,
                                "angleToParent": 2,
                                "distanceToParent": 3,
                                "arrangementStyle": 0
                            },
                            "uiObject": {
                                "isRunning": false
                            }
                        }
                    },
                    "tradingSignals": {
                        "type": "Trading Signals",
                        "name": "New Trading Signals",
                        "config": "{}",
                        "project": "Network",
                        "id": "0ad91022-aeb8-416b-a0a4-ba6d6e0681ae",
                        "savedPayload": {
                            "position": {
                                "x": 29550,
                                "y": 27320.577136594
                            },
                            "targetPosition": {
                                "x": 29550,
                                "y": 27620.577136594
                            },
                            "floatingObject": {
                                "isPinned": false,
                                "isFrozen": false,
                                "isCollapsed": false,
                                "angleToParent": 2,
                                "distanceToParent": 3,
                                "arrangementStyle": 0
                            },
                            "uiObject": {
                                "isRunning": false
                            }
                        }
                    },
                    "id": "2ff231b8-359f-4fb4-9986-60f88536c22f",
                    "savedPayload": {
                        "position": {
                            "x": 29550,
                            "y": 27620.577136594
                        },
                        "targetPosition": {
                            "x": 29700,
                            "y": 27880.384757729335
                        },
                        "floatingObject": {
                            "isPinned": false,
                            "isFrozen": false,
                            "isCollapsed": false,
                            "angleToParent": 2,
                            "distanceToParent": 3,
                            "arrangementStyle": 0
                        },
                        "uiObject": {
                            "isRunning": false
                        }
                    }
                },
                "networkInterfaces": {
                    "type": "Network Interfaces",
                    "name": "New Network Interfaces",
                    "config": "{}",
                    "project": "Network",
                    "websocketsNetworkInterface": {
                        "type": "Websockets Network Interface",
                        "name": "New Websockets Network Interface",
                        "config": "{ \n\"webSocketsPort\": \"18042\"\n}",
                        "project": "Network",
                        "id": "65f1cb2a-2a2f-4312-a216-5c0636c8691e",
                        "savedPayload": {
                            "position": {
                                "x": 29700,
                                "y": 27300.829261955892
                            },
                            "targetPosition": {
                                "x": 29777.645713530757,
                                "y": 27590.607009842613
                            },
                            "floatingObject": {
                                "isPinned": false,
                                "isFrozen": false,
                                "isCollapsed": false,
                                "angleToParent": 2,
                                "distanceToParent": 3,
                                "arrangementStyle": 0
                            },
                            "uiObject": {
                                "isRunning": false
                            }
                        }
                    },
                    "httpNetworkInterface": {
                        "type": "Http Network Interface",
                        "name": "New Http Network Interface",
                        "config": "{ \n\"httpPort\": \"31248\"\n}",
                        "project": "Network",
                        "id": "5eb5b1e0-8382-4fce-a325-402048f2c4f3",
                        "savedPayload": {
                            "position": {
                                "x": 29989.77774788672,
                                "y": 27378.47497548665
                            },
                            "targetPosition": {
                                "x": 29777.645713530757,
                                "y": 27590.607009842613
                            },
                            "floatingObject": {
                                "isPinned": false,
                                "isFrozen": false,
                                "isCollapsed": false,
                                "angleToParent": 2,
                                "distanceToParent": 3,
                                "arrangementStyle": 0
                            },
                            "uiObject": {
                                "isRunning": false
                            }
                        }
                    },
                    "id": "f7f8bc6f-ae45-4d8c-9ee4-1b5481076e95",
                    "savedPayload": {
                        "position": {
                            "x": 29777.645713530757,
                            "y": 27590.607009842613
                        },
                        "targetPosition": {
                            "x": 29700,
                            "y": 27880.384757729335
                        },
                        "floatingObject": {
                            "isPinned": false,
                            "isFrozen": false,
                            "isCollapsed": false,
                            "angleToParent": 2,
                            "distanceToParent": 3,
                            "arrangementStyle": 0
                        },
                        "uiObject": {
                            "isRunning": false
                        }
                    }
                },
                "id": "48d0b3c3-0af3-4e18-a843-d04be75aeb81",
                "savedPayload": {
                    "position": {
                        "x": 29700,
                        "y": 27880.384757729335
                    },
                    "targetPosition": {
                        "x": 29850,
                        "y": 28140.192378864667
                    },
                    "floatingObject": {
                        "isPinned": false,
                        "isFrozen": false,
                        "isCollapsed": false,
                        "angleToParent": 1,
                        "distanceToParent": 3,
                        "arrangementStyle": 0
                    },
                    "uiObject": {
                        "isRunning": false
                    }
                }
            }
        ],
        "id": "ff4ee065-91a9-485c-b2f7-ea26c6b675be",
        "savedPayload": {
            "position": {
                "x": 29850,
                "y": 28140.192378864667
            },
            "targetPosition": {
                "x": 30000,
                "y": 28400
            },
            "floatingObject": {
                "isPinned": false,
                "isFrozen": false,
                "isCollapsed": false,
                "angleToParent": 1,
                "distanceToParent": 3,
                "arrangementStyle": 0
            },
            "uiObject": {
                "isRunning": false
            }
        }
    },
    "userStorage": {
        "type": "User Storage",
        "name": "New User Storage",
        "config": "{}",
        "project": "Open-Storage",
        "githubStorage": {
            "type": "Github Storage",
            "name": "New Github Storage",
            "config": "{}",
            "project": "Open-Storage",
            "githubStorageContainers": [
                {
                    "type": "Github Storage Container",
                    "name": "Social Trading Data",
                    "config": "{\n\"codeName\": \"Github-Alcrano-Social-Trading-Data\",\n\"githubUserName\": \"NAmorim\",\n\"repositoryName\": \"Alcrano-Social-Trading-Data\"\n}",
                    "project": "Open-Storage",
                    "id": "c89c79ff-273b-4a4d-b455-55a9ff0145ba",
                    "savedPayload": {
                        "position": {
                            "x": 30450,
                            "y": 27620.577136594
                        },
                        "targetPosition": {
                            "x": 30300,
                            "y": 27880.384757729335
                        },
                        "floatingObject": {
                            "isPinned": false,
                            "isFrozen": false,
                            "isCollapsed": false,
                            "angleToParent": 1,
                            "distanceToParent": 3,
                            "arrangementStyle": 0
                        },
                        "uiObject": {
                            "isRunning": false
                        }
                    }
                }
            ],
            "id": "97b5ee6a-6cb3-4305-9b3f-b046df0aef49",
            "savedPayload": {
                "position": {
                    "x": 30300,
                    "y": 27880.384757729335
                },
                "targetPosition": {
                    "x": 30150,
                    "y": 28140.192378864667
                },
                "floatingObject": {
                    "isPinned": false,
                    "isFrozen": false,
                    "isCollapsed": false,
                    "angleToParent": 1,
                    "distanceToParent": 3,
                    "arrangementStyle": 0
                },
                "uiObject": {
                    "isRunning": false
                }
            }
        },
        "id": "cb851ce0-af79-4b66-bd52-918625ce7a31",
        "savedPayload": {
            "position": {
                "x": 30150,
                "y": 28140.192378864667
            },
            "targetPosition": {
                "x": 30000,
                "y": 28400
            },
            "floatingObject": {
                "isPinned": false,
                "isFrozen": false,
                "isCollapsed": false,
                "angleToParent": 1,
                "distanceToParent": 3,
                "arrangementStyle": 0
            },
            "uiObject": {
                "isRunning": false
            }
        }
    },
    "id": "56da7a9b-9058-46f4-8c10-a7f9ce2351ea",
    "savedPayload": {
        "position": {
            "x": 30000,
            "y": 28400
        },
        "targetPosition": {
            "x": 30000,
            "y": 28400
        },
        "floatingObject": {
            "isPinned": false,
            "isFrozen": false,
            "isCollapsed": false,
            "angleToParent": 1,
            "distanceToParent": 3,
            "arrangementStyle": 0
        },
        "uiObject": {
            "isRunning": false
        }
    }
}